dcmri/__init__.py
dcmri/data.py
dcmri/fake.py
dcmri/kidney.py
dcmri/lib.py
dcmri/liver.py
dcmri/pk.py
dcmri/pk_aorta.py
dcmri/pk_inv.py
dcmri/pk_lib.py
dcmri/rel.py
dcmri/sig.py
dcmri/tissue.py
dcmri/ui.py
dcmri/ui_aorta.py
dcmri/ui_aorta_kidneys.py
dcmri/ui_aorta_liver.py
dcmri/ui_aorta_portal_liver.py
dcmri/ui_kidney.py
dcmri/ui_kidney_cortmed.py
dcmri/ui_liver.py
dcmri/ui_tissue.py
dcmri/ui_tissue_ls.py
dcmri/ui_tissue_ls_array.py
dcmri/utils.py
dcmri/datafiles/__init__.py
dcmri-0.6.19.dist-info/licenses/LICENSE
dcmri-0.6.19.dist-info/METADATA
dcmri-0.6.19.dist-info/WHEEL
dcmri-0.6.19.dist-info/top_level.txt
dcmri-0.6.19.dist-info/RECORD
