Metadata-Version: 2.4
Name: dcmri
Version: 0.6.19
Summary: A python toolbox for dynamic contrast MRI
Author-email: Steven Sourbron <s.sourbron@sheffield.ac.uk>, Ebony Gunwhy <e.gunwhy@sheffield.ac.uk>, Eve Shalom <E.S.Shalom@sheffield.ac.uk>
License:                                  Apache License
Project-URL: Homepage, https://dcmri.org
Project-URL: Source Code, https://github.com/dcmri/dcmri
Keywords: python,medical imaging,perfusion,MRI
Classifier: Development Status :: 3 - Alpha
Classifier: Intended Audience :: Developers
Classifier: Intended Audience :: Science/Research
Classifier: Topic :: Scientific/Engineering
Classifier: Operating System :: OS Independent
Classifier: License :: OSI Approved :: Apache Software License
Classifier: Programming Language :: Python
Classifier: Programming Language :: Python :: 3
Requires-Python: >=3.10
License-File: LICENSE
Requires-Dist: importlib-resources>=1.1.0
Requires-Dist: tqdm
Requires-Dist: numpy
Requires-Dist: scipy
Requires-Dist: matplotlib
Requires-Dist: requests
Dynamic: license-file
